askell/__init__.py
askell/admin.py
askell/apps.py
askell/client.py
askell/context_processor.py
askell/models.py
askell/settings.py
askell/urls.py
askell/utils.py
askell/views.py
askell/webhook_handlers.py
askell/webhooks.py
askell/management/__init__.py
askell/management/commands/__init__.py
askell/management/commands/sync_plans.py
askell/migrations/0001_initial.py
askell/migrations/0002_payment_amount_payment_currency.py
askell/migrations/0003_payment_user.py
askell/migrations/0004_remove_payment_user_payment_uuid_alter_payment_id.py
askell/migrations/0005_payment_user.py
askell/migrations/0006_remove_payment_settled_remove_payment_settled_at_and_more.py
askell/migrations/0007_plan.py
askell/migrations/__init__.py
askell/wagtail/__init__.py
askell/wagtail/admin.py
askell/wagtail/apps.py
askell/wagtail/models.py
askell/wagtail/tests.py
askell/wagtail/views.py
django_askell-0.1.24.dist-info/METADATA
django_askell-0.1.24.dist-info/WHEEL
django_askell-0.1.24.dist-info/top_level.txt
django_askell-0.1.24.dist-info/RECORD
